destrobe/__init__.py
destrobe/cli.py
destrobe/core/__init__.py
destrobe/core/enhanced_filters.py
destrobe/core/extreme_filters.py
destrobe/core/filters.py
destrobe/core/hyperextreme_filters.py
destrobe/core/io.py
destrobe/core/metrics.py
destrobe/core/preview.py
destrobe/core/simple_preview.py
destrobe/core/ultra_filters.py
destrobe/utils/__init__.py
destrobe/utils/fps.py
destrobe/utils/logging.py
destrobe-1.0.0.dist-info/licenses/LICENSE
destrobe-1.0.0.dist-info/METADATA
destrobe-1.0.0.dist-info/WHEEL
destrobe-1.0.0.dist-info/entry_points.txt
destrobe-1.0.0.dist-info/top_level.txt
destrobe-1.0.0.dist-info/RECORD
