Metadata-Version: 2.4
Name: destrobe
Version: 1.0.0
Summary: Cross-platform CLI tool for reducing video strobing and flicker while preserving audio and sync
Author-email: Sam Hill <sam@samjhill.com>
License-Expression: MIT
Project-URL: Homepage, https://github.com/samhilll/destrobe
Project-URL: Repository, https://github.com/samhilll/destrobe
Project-URL: Issues, https://github.com/samhilll/destrobe/issues
Keywords: video,flicker,strobe,photosensitive,epilepsy,accessibility,cli
Classifier: Development Status :: 5 - Production/Stable
Classifier: Intended Audience :: End Users/Desktop
Classifier: Intended Audience :: Healthcare Industry
Classifier: Operating System :: OS Independent
Classifier: Programming Language :: Python :: 3
Classifier: Programming Language :: Python :: 3.10
Classifier: Programming Language :: Python :: 3.11
Classifier: Programming Language :: Python :: 3.12
Classifier: Topic :: Multimedia :: Video
Classifier: Topic :: Scientific/Engineering :: Image Processing
Classifier: Topic :: Utilities
Classifier: Environment :: Console
Requires-Python: >=3.10
License-File: LICENSE
Requires-Dist: opencv-python>=4.8.0
Requires-Dist: numpy>=1.24.0
Requires-Dist: tqdm>=4.65.0
Requires-Dist: scikit-image>=0.21.0
Requires-Dist: typer>=0.9.0
Requires-Dist: rich>=13.0.0
Provides-Extra: dev
Requires-Dist: pytest>=7.0.0; extra == "dev"
Requires-Dist: pytest-xdist>=3.0.0; extra == "dev"
Requires-Dist: ruff>=0.1.0; extra == "dev"
Requires-Dist: black>=23.0.0; extra == "dev"
Requires-Dist: mypy>=1.5.0; extra == "dev"
Dynamic: license-file
